diffusion_image_gen/__init__.py
diffusion_image_gen/base.py
diffusion_image_gen/cli.py
diffusion_image_gen/score_model.py
diffusion_image_gen/utils.py
diffusion_image_gen/visualization.py
diffusion_image_gen/dashboard/assets/styles.css
diffusion_image_gen/dashboard/locales/cn.json
diffusion_image_gen/dashboard/locales/en.json
diffusion_image_gen/dashboard/locales/es.json
diffusion_image_gen/dashboard_app/__init__.py
diffusion_image_gen/dashboard_app/main_dashboard.py
diffusion_image_gen/dashboard_app/.streamlit/config.toml
diffusion_image_gen/diffusion/__init__.py
diffusion_image_gen/diffusion/base.py
diffusion_image_gen/diffusion/sub_vp.py
diffusion_image_gen/diffusion/ve.py
diffusion_image_gen/diffusion/vp.py
diffusion_image_gen/metrics/__init__.py
diffusion_image_gen/metrics/base.py
diffusion_image_gen/metrics/bpd.py
diffusion_image_gen/metrics/fid.py
diffusion_image_gen/metrics/inception.py
diffusion_image_gen/noise/__init__.py
diffusion_image_gen/noise/base.py
diffusion_image_gen/noise/cosine.py
diffusion_image_gen/noise/linear.py
diffusion_image_gen/samplers/__init__.py
diffusion_image_gen/samplers/base.py
diffusion_image_gen/samplers/euler_maruyama.py
diffusion_image_gen/samplers/exponential.py
diffusion_image_gen/samplers/ode.py
diffusion_image_gen/samplers/predictor_corrector.py
tests/__init__.py
tests/context.py
tests/test_base.py
tests/test_diffusion.py
tests/test_integration.py
tests/test_metrics.py
tests/test_noise.py
tests/test_samplers.py
diffusion_image_gen-0.4.1.dist-info/LICENSE
diffusion_image_gen-0.4.1.dist-info/METADATA
diffusion_image_gen-0.4.1.dist-info/WHEEL
diffusion_image_gen-0.4.1.dist-info/entry_points.txt
diffusion_image_gen-0.4.1.dist-info/top_level.txt
diffusion_image_gen-0.4.1.dist-info/RECORD
