Metadata-Version: 2.1
Name: diffusion-image-gen
Version: 0.4.1
Summary: A package for generating images with diffusion
Author: Héctor Tablero Díaz, Álvaro Martínez Gamo
Author-email: Héctor Tablero Díaz <hector.tablerodiaz@gmail.com>, Álvaro Martínez Gamo <alva00003@gmail.com>
License: MIT
Project-URL: Homepage, https://github.com/HectorTablero/image-gen
Project-URL: Issues, https://github.com/HectorTablero/image-gen/issues
Classifier: Programming Language :: Python :: 3
Classifier: Operating System :: OS Independent
Requires-Python: >=3.8
License-File: LICENSE
Requires-Dist: torch >=2.0.0
Requires-Dist: torchvision >=0.15.0
Requires-Dist: numpy >=1.20.0
Requires-Dist: scipy >=1.7.0
Requires-Dist: Pillow >=9.0.0
Requires-Dist: matplotlib >=3.5.0
Requires-Dist: streamlit >=1.20.0
Requires-Dist: toml >=0.10.2
Requires-Dist: tqdm >=4.64.0
Requires-Dist: ipython >=8.0.0
Requires-Dist: dill >=0.3.5
